setup.py
SPACEisCool.egg-info/PKG-INFO
SPACEisCool.egg-info/SOURCES.txt
SPACEisCool.egg-info/dependency_links.txt
SPACEisCool.egg-info/top_level.txt
space/__init__.py
space/astronomy.py
space/weather.py
space/bodies/__init__.py
space/bodies/asteroids.py
space/bodies/earth.py
space/bodies/exoplanets.py
space/bodies/stars.py
space/bodies/sun.py
space/imagery/__init__.py
space/imagery/mars.py
space/imagery/moon.py
space/imagery/vesta.py
space/research/__init__.py
space/research/genelab.py
space/research/spacex.py
space/satellites/EPIC.py
space/satellites/__init__.py
space/satellites/landsat8.py