Metadata-Version: 1.0
Name: SPACEisCool
Version: 0.1
Summary: get all the data about space
Home-page: UNKNOWN
Author: jarbasAI
Author-email: jarbasai@mailfence.com
License: MIT
Platform: UNKNOWN
